fsb/__init__.py
fsb/bundle.py
fsb/models.py
fsb/schemas.py
fsb/schemas/data_info.schema.json
fsb/schemas/encoding.schema.json
fsb/schemas/node.schema.json
fsb/schemas/render_manifest.schema.json
fsb/schemas/stats.schema.json
fsb/schemas/theme.schema.json
fsb-0.1.1.dist-info/licenses/LICENSE
fsb-0.1.1.dist-info/METADATA
fsb-0.1.1.dist-info/WHEEL
fsb-0.1.1.dist-info/top_level.txt
fsb-0.1.1.dist-info/RECORD
