Metadata-Version: 2.4
Name: fsb
Version: 0.1.1
Summary: Figure-Statistics Bundle: A specification for reproducible scientific figures
Author-email: Yusuke Watanabe <ywatanabe@scitex.ai>
License: AGPL-3.0
Project-URL: Homepage, https://github.com/ywatanabe1989/fsb
Project-URL: Documentation, https://github.com/ywatanabe1989/fsb#readme
Project-URL: Repository, https://github.com/ywatanabe1989/fsb
Project-URL: Issues, https://github.com/ywatanabe1989/fsb/issues
Keywords: scientific-figures,reproducibility,visualization,statistics,data-science
Classifier: Development Status :: 3 - Alpha
Classifier: Intended Audience :: Science/Research
Classifier: License :: OSI Approved :: GNU Affero General Public License v3
Classifier: Programming Language :: Python :: 3
Classifier: Programming Language :: Python :: 3.9
Classifier: Programming Language :: Python :: 3.10
Classifier: Programming Language :: Python :: 3.11
Classifier: Programming Language :: Python :: 3.12
Classifier: Topic :: Scientific/Engineering :: Visualization
Requires-Python: >=3.9
License-File: LICENSE
Requires-Dist: jsonschema>=4.0
Requires-Dist: pandas>=1.5
Provides-Extra: dev
Requires-Dist: pytest>=7.0; extra == "dev"
Requires-Dist: pytest-cov>=4.0; extra == "dev"
Requires-Dist: black>=23.0; extra == "dev"
Requires-Dist: ruff>=0.1; extra == "dev"
Provides-Extra: plotting
Requires-Dist: matplotlib>=3.5; extra == "plotting"
Requires-Dist: numpy>=1.20; extra == "plotting"
Provides-Extra: stats
Requires-Dist: scipy>=1.9; extra == "stats"
Requires-Dist: statsmodels>=0.14; extra == "stats"
Provides-Extra: all
Requires-Dist: fsb[plotting,stats]; extra == "all"
Dynamic: license-file
